advpython2025/__init__.py
advpython2025/complex.py
advpython2025-0.1.6.dist-info/METADATA
advpython2025-0.1.6.dist-info/WHEEL
advpython2025-0.1.6.dist-info/RECORD
